{
    "epkgs": {
        "cargoLock": null,
        "date": "2026-06-08",
        "extract": null,
        "name": "epkgs",
        "passthru": null,
        "pinned": false,
        "src": {
            "deepClone": false,
            "fetchSubmodules": false,
            "leaveDotGit": false,
            "name": null,
            "owner": "emacsmirror",
            "repo": "epkgs",
            "rev": "14787042821c03a922ae43b0988635558e01dfd1",
            "sha256": "sha256-o4254CxEMPByzrntG+O91vyVLl4oVwQn+cLJ23aBwtQ=",
            "sparseCheckout": [],
            "type": "github"
        },
        "version": "14787042821c03a922ae43b0988635558e01dfd1"
    },
    "gnu-elpa": {
        "cargoLock": null,
        "date": "2026-06-12",
        "extract": null,
        "name": "gnu-elpa",
        "passthru": null,
        "pinned": false,
        "src": {
            "deepClone": false,
            "fetchSubmodules": false,
            "leaveDotGit": false,
            "name": null,
            "owner": "elpa-mirrors",
            "repo": "elpa",
            "rev": "f88cdce39b6e4162059bf39af4319c2956e48ca2",
            "sha256": "sha256-nhrJP0zu1yuNgATAvjFqqIGRNqX4UHDtoG5qcwg+YyQ=",
            "sparseCheckout": [],
            "type": "github"
        },
        "version": "f88cdce39b6e4162059bf39af4319c2956e48ca2"
    },
    "melpa": {
        "cargoLock": null,
        "date": "2026-06-09",
        "extract": null,
        "name": "melpa",
        "passthru": null,
        "pinned": false,
        "src": {
            "deepClone": false,
            "fetchSubmodules": false,
            "leaveDotGit": false,
            "name": null,
            "owner": "melpa",
            "repo": "melpa",
            "rev": "5db2cf30d09370389c33ac6ee13d79b2edcf058f",
            "sha256": "sha256-SfzygE69RSdy8s9IpXB2elUlCAfE9DqTxVw+0QzOuOg=",
            "sparseCheckout": [],
            "type": "github"
        },
        "version": "5db2cf30d09370389c33ac6ee13d79b2edcf058f"
    },
    "nongnu-elpa": {
        "cargoLock": null,
        "date": "2026-06-09",
        "extract": null,
        "name": "nongnu-elpa",
        "passthru": null,
        "pinned": false,
        "src": {
            "deepClone": false,
            "fetchSubmodules": false,
            "leaveDotGit": false,
            "name": null,
            "owner": "elpa-mirrors",
            "repo": "nongnu",
            "rev": "3253fbf43762ee4310b414aa45473898b814762f",
            "sha256": "sha256-LIUL6R+/HY+TV3g3kak5XCktLm4ejkie3vC/Z/AG+Ts=",
            "sparseCheckout": [],
            "type": "github"
        },
        "version": "3253fbf43762ee4310b414aa45473898b814762f"
    }
}